[
  {
    "id": "mhlqiw6xbbyw3x3vkaq",
    "agentId": "gHlVBWm87pygVY6EQJVL",
    "agentName": "Adobe 2025 Max Announcement",
    "text": "Adobe Max 2025 announced over 200 new features, including the launch of GenStudio, enhancing creative workflows significantly with AI-driven tools.",
    "status": "reported",
    "stepTitle": "Compile Preliminary Findings",
    "stepIndex": 1,
    "phase": 4,
    "sequence": 0,
    "supportingData": null,
    "timestamp": "2025-11-05T08:27:31.062Z",
    "reportedAt": "2025-11-05T08:27:31.065Z"
  }
]